mapperr/__init__.py
mapperr/mapr.py
mapperr-0.0.5.dist-info/LICENSE
mapperr-0.0.5.dist-info/METADATA
mapperr-0.0.5.dist-info/WHEEL
mapperr-0.0.5.dist-info/top_level.txt
mapperr-0.0.5.dist-info/RECORD
