Metadata-Version: 2.1
Name: mapperr
Version: 0.0.5
Summary: mapperr for mapping across dict and object, recursively
Home-page: https://github.com/mujdecisy/mapperr
Author: mujdecisy
Author-email: mujdecisy@gmail.com
License: UNKNOWN
Keywords: python,mapper,recursive mapping
Platform: UNKNOWN
Classifier: Programming Language :: Python :: 3
License-File: LICENSE
